anji_common_addons/__init__.py
anji_common_addons/git.py
anji_common_addons/make.py
anji_common_addons/odoo.py
anji_common_addons-0.3.2.dist-info/DESCRIPTION.rst
anji_common_addons-0.3.2.dist-info/METADATA
anji_common_addons-0.3.2.dist-info/RECORD
anji_common_addons-0.3.2.dist-info/WHEEL
anji_common_addons-0.3.2.dist-info/metadata.json
anji_common_addons-0.3.2.dist-info/top_level.txt
