Metadata-Version: 2.0
Name: anji-common-addons
Version: 0.3.2
Summary: Common addons for AnjiProject
Home-page: https://gitlab.com/AnjiProject/anji-common-addons
Author: Bogdan Gladyshev
Author-email: siredvin.dark@gmail.com
License: MIT license
Keywords: chatops errbot slack telegram
Platform: UNKNOWN
Classifier: Development Status :: 5 - Production/Stable
Classifier: Intended Audience :: Developers
Classifier: License :: OSI Approved :: MIT License
Classifier: Natural Language :: English
Classifier: Programming Language :: Python :: 3.5
Classifier: Programming Language :: Python :: 3.6
Requires-Dist: anji-core (>=0.8.8)
